transcraipt/__init__.py
transcraipt/__main__.py
transcraipt/transcript.py
transcraipt-0.1.76.dist-info/METADATA
transcraipt-0.1.76.dist-info/WHEEL
transcraipt-0.1.76.dist-info/entry_points.txt
transcraipt-0.1.76.dist-info/license.txt
transcraipt-0.1.76.dist-info/top_level.txt
transcraipt-0.1.76.dist-info/RECORD
