Metadata-Version: 2.1
Name: transcraipt
Version: 0.1.76
Summary: A tool for transcribing audio files using OpenAI's API
Home-page: https://github.com/gsusI/audio_transcript
Author: Jesus Iniesta
Author-email: jesus.inica@gmail.com
Classifier: Programming Language :: Python :: 3
Classifier: License :: OSI Approved :: MIT License
Classifier: Operating System :: OS Independent
Requires-Python: >=3.6
License-File: license.txt
Requires-Dist: openai >=1.12.0
Requires-Dist: requests >=2.31.0
Requires-Dist: tqdm >=4.66.1
Requires-Dist: argcomplete >=3.2.2
